cxnetwork.cpython-37m-darwin.so
cxnetwork-0.1.dist-info/LICENSE
cxnetwork-0.1.dist-info/METADATA
cxnetwork-0.1.dist-info/WHEEL
cxnetwork-0.1.dist-info/top_level.txt
cxnetwork-0.1.dist-info/RECORD
