Metadata-Version: 2.1
Name: cxnetwork
Version: 0.1
Summary: Experimental library to analyze complex networks
Home-page: https://github.com/filipinascimento/cxnetwork
Author: Filipi N. Silva
Author-email: filipi@iu.edu
License: UNKNOWN
Platform: UNKNOWN
Classifier: Programming Language :: Python :: 3
Classifier: License :: OSI Approved :: MIT License
Classifier: Operating System :: OS Independent
Requires-Python: >=3.0
